{
  "books": [
    {
      "title": "Getting Started",
      "slug": "getting-started",
      "chapters": [
        {
          "title": "Hello, World!",
          "slug": "hello-world",
          "file": "getting-started/hello-world.md"
        },
        {
          "title": "Storing Data",
          "slug": "data-storage",
          "file": "getting-started/data-storage.md"
        },
        {
          "title": "Building a Web App",
          "slug": "web-app",
          "file": "getting-started/web-app.md"
        }
      ]
    },
    {
      "title": "Reference",
      "slug": "reference",
      "chapters": [
        {
          "title": "Component",
          "slug": "component",
          "file": "reference/component.md",
          "source": [
            "../packages/component/src/component.ts",
            "../packages/component/src/cloning.ts",
            "../packages/component/src/forking.ts",
            "../packages/component/src/merging.ts",
            "../packages/component/src/serialization.ts",
            "../packages/component/src/deserialization.ts",
            "../packages/component/src/decorators.ts",
            "../packages/component/src/utilities.ts"
          ]
        },
        {
          "title": "EmbeddedComponent",
          "slug": "embedded-component",
          "file": "reference/embedded-component.md",
          "source": "../packages/component/src/embedded-component.ts"
        },
        {
          "title": "Property",
          "slug": "property",
          "file": "reference/property.md",
          "source": "../packages/component/src/properties/property.ts"
        },
        {
          "title": "Attribute",
          "slug": "attribute",
          "file": "reference/attribute.md",
          "source": "../packages/component/src/properties/attribute.ts"
        },
        {
          "title": "AttributeSelector",
          "slug": "attribute-selector",
          "file": "reference/attribute-selector.md",
          "source": "../packages/component/src/properties/attribute-selector.ts"
        },
        {
          "title": "IdentifierAttribute",
          "slug": "identifier-attribute",
          "file": "reference/identifier-attribute.md",
          "source": "../packages/component/src/properties/identifier-attribute.ts"
        },
        {
          "title": "PrimaryIdentifierAttribute",
          "slug": "primary-identifier-attribute",
          "file": "reference/primary-identifier-attribute.md",
          "source": "../packages/component/src/properties/primary-identifier-attribute.ts"
        },
        {
          "title": "SecondaryIdentifierAttribute",
          "slug": "secondary-identifier-attribute",
          "file": "reference/secondary-identifier-attribute.md",
          "source": "../packages/component/src/properties/secondary-identifier-attribute.ts"
        },
        {
          "title": "IdentityMap",
          "slug": "identity-map",
          "file": "reference/identity-map.md",
          "source": "../packages/component/src/identity-map.ts"
        },
        {
          "title": "ValueType",
          "slug": "value-type",
          "file": "reference/value-type.md",
          "source": "../packages/component/src/properties/value-types/value-type.ts"
        },
        {
          "title": "Validator",
          "slug": "validator",
          "file": "reference/validator.md",
          "source": "../packages/component/src/validation/validator.ts"
        },
        {
          "title": "Method",
          "slug": "method",
          "file": "reference/method.md",
          "source": "../packages/component/src/properties/method.ts"
        },
        {
          "title": "ComponentClient",
          "slug": "component-client",
          "file": "reference/component-client.md",
          "source": "../packages/component-client/src/component-client.ts"
        },
        {
          "title": "ComponentServer",
          "slug": "component-server",
          "file": "reference/component-server.md",
          "source": "../packages/component-server/src/component-server.ts"
        },
        {
          "title": "ComponentHTTPClient",
          "slug": "component-http-client",
          "file": "reference/component-http-client.md",
          "source": "../packages/component-http-client/src/component-http-client.ts"
        },
        {
          "title": "ComponentHTTPServer",
          "slug": "component-http-server",
          "file": "reference/component-http-server.md",
          "source": "../packages/component-http-server/src/component-http-server.ts"
        },
        {
          "title": "component-express-middleware",
          "slug": "component-express-middleware",
          "file": "reference/component-express-middleware.md",
          "source": "../packages/component-express-middleware/src/component-express-middleware.ts"
        },
        {
          "title": "component-koa-middleware",
          "slug": "component-koa-middleware",
          "file": "reference/component-koa-middleware.md",
          "source": "../packages/component-koa-middleware/src/component-koa-middleware.ts"
        }
      ]
    }
  ]
}
